Metadata-Version: 1.0
Name: quanter
Version: 0.2
Summary: add function
Home-page: UNKNOWN
Author: hugo
Author-email: UNKNOWN
License: MIT
Platform: UNKNOWN
